README.md
background_mask.py
setup.py
background_mask.egg-info/PKG-INFO
background_mask.egg-info/SOURCES.txt
background_mask.egg-info/dependency_links.txt
background_mask.egg-info/entry_points.txt
background_mask.egg-info/requires.txt
background_mask.egg-info/top_level.txt